{"components_coloranimatetext.md":"fe622f84","components_demo.md":"3baaa599","components_crop.md":"0ccfec7c","components_countto.md":"9c838ff4","utils_watermark.md":"6cb429db","docs_quickstart.md":"1f1274c7","index.md":"0d75a58a","utils_color-thief.md":"85136867","utils_date.md":"fa6aeb40","utils_download.md":"5a97e2ba","utils_index.md":"f1c23079","utils_integration.md":"1eb5a79c","utils_localstorage.md":"8a7807f6","utils_sessionstorage.md":"90c1abae","utils_typescript.md":"94f1dc2b","utils_canvassign.md":"a8348d17","components_rotatemenu.md":"be92c0f3","docs_installation.md":"ff65afce"}
